{
  "status": 0,
  "message": [
    {
      "id": 1,
      "title": "图片111111111",
      "img_url": "../../../static/img/lunBo/1.png",
      "zhaiyao": "photo22222222"
    },
    {
      "id": 2,
      "title": "图片111111111",
      "img_url": "../../../static/img/lunBo/2.png",
      "zhaiyao": "photo22222222"
    },
    {
      "id": 3,
      "title": "图片2222222222",
      "img_url": "../../../static/img/lunBo/3.png",
      "zhaiyao": "photo33333333333333"
    },
    {
      "id": 4,
      "title": "图片2222222222222",
      "img_url": "../../../static/img/lunBo/4.png",
      "zhaiyao": "photo44444444"
    },
    {
      "id": 5,
      "title": "图片3333333333",
      "img_url": "../../../static/img/lunBo/2.png",
      "zhaiyao": "photo22222222"
    },
    {
      "id": 6,
      "title": "图片3333333333333",
      "img_url": "../../../static/img/lunBo/3.png",
      "zhaiyao": "photo33333333333333"
    },
    {
      "id": 7,
      "title": "图片4444444444444",
      "img_url": "../../../static/img/lunBo/4.png",
      "zhaiyao": "photo44444444"
    },
    {
      "id": 8,
      "title": "图片4444444444",
      "img_url": "../../../static/img/lunBo/2.png",
      "zhaiyao": "photo22222222"
    },
    {
      "id": 9,
      "title": "图片44444444444",
      "img_url": "../../../static/img/lunBo/3.png",
      "zhaiyao": "photo33333333333333"
    },
    {
      "id": 10,
      "title": "图片4444444444444",
      "img_url": "../../../static/img/lunBo/4.png",
      "zhaiyao": "photo44444444"
    }
  ]
}
